apidaora/__init__.py
apidaora/app.py
apidaora/bodies.py
apidaora/class_controller.py
apidaora/content.py
apidaora/exceptions.py
apidaora/header.py
apidaora/method.py
apidaora/middlewares.py
apidaora/options.py
apidaora/py.typed
apidaora/request.py
apidaora/responses.py
apidaora/asgi/__init__.py
apidaora/asgi/app.py
apidaora/asgi/base.py
apidaora/asgi/request.py
apidaora/asgi/responses.py
apidaora/asgi/router.py
apidaora/controllers/__init__.py
apidaora/controllers/background_task.py
apidaora/core/__init__.py
apidaora/core/decorator.py
apidaora/route/__init__.py
apidaora/route/annotations_getters.py
apidaora/route/controller_input.py
apidaora/route/decorator.py
apidaora/route/factory.py
apidaora-0.28.0.dist-info/LICENSE
apidaora-0.28.0.dist-info/WHEEL
apidaora-0.28.0.dist-info/METADATA
apidaora-0.28.0.dist-info/RECORD
